{
	"": "API specification",
	"apiIdentifier": "egl",
	"sourceUrl": "https://raw.githubusercontent.com/KhronosGroup/EGL-Registry/master/api/egl.xml",
	"sourceFile": "egl.xml",

	"": "Parser configuration",
	"parser": "egl",

	"": "Identifier parsing",
	"lowercasePrefix": "egl",
	"uppercasePrefix": "EGL_",

	"": "Meta Feature management",
	"generator": "cpp",
	"bindingNamespace": "eglbinding",
	"baseNamespace": "egl",
	"generateFeatures": true,
	"generateProfiles": true,
	"coreProfileSince": null,
	"multiContext": true,
	"generateStringLookup": true,
	"generateStringConversion": true,
	"generateCallbacks": true,
	"generateLogging": true,
	"generateHeaderGuard": true,
	"headerGuardMacro": [ "__egl_h_" ],
	"headerReplacement": [ "egl.h" ],

	"": "Types",
	"extensionType": "EGLextension",
	"booleanType": "EGLBoolean",
	"booleanWidth": 8,
	"enumType": "EGLenum",
	"bitfieldType": "EGLbitfield",
	"noneBitfieldValue": "EGL_NONE_BIT",

	"": "API Feature management",
	"apiIdentifier": "egl",
	"versions": [],
	"featureBlacklist": [],
	"extensionBlacklist": [],
	"useBitfieldGroups": true,
	"useEnumGroups": false,
	"generateNoneBits": true,
	"generateBitfieldTypeIntegrations": true,
	"generateEnumTypeIntegrations": true,

	"": "File patterns"
}